xyw_macro/__init__.py
xyw_macro/command.py
xyw_macro/contants.py
xyw_macro/hook.py
xyw_macro/macro.py
xyw_macro/notify.py
xyw_macro/utils.py
xyw_macro/win32.py
xyw_macro-0.0.16.dist-info/LICENSE
xyw_macro-0.0.16.dist-info/METADATA
xyw_macro-0.0.16.dist-info/WHEEL
xyw_macro-0.0.16.dist-info/top_level.txt
xyw_macro-0.0.16.dist-info/RECORD
