Metadata-Version: 2.1
Name: xyw-macro
Version: 0.0.16
Summary: 键盘宏，可根据需要自定义多套功能键区。
Home-page: UNKNOWN
Author: 二炜
Author-email: 1174543101@qq.com
License: UNKNOWN
Platform: UNKNOWN
Classifier: Programming Language :: Python :: 3
Classifier: License :: OSI Approved :: MIT License
Classifier: Operating System :: Microsoft :: Windows
Requires-Dist: pywin32
Requires-Dist: simpleaudio
